transmit_db/__init__.py
transmit_db/log.py
transmit_db/transmit.py
transmit_db/transmit_func.py
transmit_db/transmit_type.py
transmit_db/util.py
transmit_db/with_cursor.py
transmitDB-1.0.dist-info/LICENSE
transmitDB-1.0.dist-info/METADATA
transmitDB-1.0.dist-info/WHEEL
transmitDB-1.0.dist-info/top_level.txt
transmitDB-1.0.dist-info/RECORD
